PackageSnippet1/__init__.py
PackageSnippet1/subpackage1/__init__.py
PackageSnippet1/subpackage1/moduleA.py
PackageSnippet1/subpackage2/__init__.py
PackageSnippet1/subpackage2/moduleB.py
PackageSnippet1-0.0.6.dist-info/LICENSE
PackageSnippet1-0.0.6.dist-info/METADATA
PackageSnippet1-0.0.6.dist-info/WHEEL
PackageSnippet1-0.0.6.dist-info/top_level.txt
PackageSnippet1-0.0.6.dist-info/RECORD
