Metadata-Version: 2.1
Name: PackageSnippet1
Version: 0.0.6
Summary: Common utils package
Home-page: https://github.com/user/reponame
Author: Jerin KA
Author-email: me@example.com
License: UNKNOWN
Download-URL: https://github.com/user/reponame/archive/v_01.tar.gz
Keywords: SOME,MEANINGFULL,KEYWORDS
Platform: UNKNOWN
License-File: LICENSE
Requires-Dist: pytest
